steam_totp/__init__.py
steam_totp-0.1.2.dist-info/LICENSE
steam_totp-0.1.2.dist-info/WHEEL
steam_totp-0.1.2.dist-info/METADATA
steam_totp-0.1.2.dist-info/RECORD
