Metadata-Version: 2.1
Name: steam-totp
Version: 0.1.2
Summary: Python library to generate Steam-style TOTP auth codes
Home-page: https://github.com/shabbywu/python-steam-totp
License: Apache-2.0
Author: shabbywu
Author-email: shabbywu@qq.com
Requires-Python: >=2.7,<4.0
Classifier: License :: OSI Approved :: Apache Software License
Classifier: Programming Language :: Python :: 2
Classifier: Programming Language :: Python :: 2.7
Classifier: Programming Language :: Python :: 3
Classifier: Programming Language :: Python :: 3.10
Classifier: Programming Language :: Python :: 3.4
Classifier: Programming Language :: Python :: 3.5
Classifier: Programming Language :: Python :: 3.6
Classifier: Programming Language :: Python :: 3.7
Classifier: Programming Language :: Python :: 3.8
Classifier: Programming Language :: Python :: 3.9
Requires-Dist: dataclasses (==0.7); python_version < "3.5"
Project-URL: Repository, https://github.com/shabbywu/python-steam-totp
